.DS_Store
DataProfileViewer/__init__.py
DataProfileViewer/_comm_api.py
DataProfileViewer/_demodata.py
DataProfileViewer/_plot_metadata_table.py
DataProfileViewer/build/dataProfileVis.js
DataProfileViewer/data/lifeexpectancydata.csv
data_profile_viewer-0.2.7.dist-info/LICENSE
data_profile_viewer-0.2.7.dist-info/METADATA
data_profile_viewer-0.2.7.dist-info/WHEEL
data_profile_viewer-0.2.7.dist-info/top_level.txt
data_profile_viewer-0.2.7.dist-info/RECORD
