Metadata-Version: 2.1
Name: data-profile-viewer
Version: 0.2.7
Summary: Data Profile Viewer tool. Enables the exploration of data profile in Jupyter Notebooks
Home-page: https://github.com/soniacq/DataProfileVis
Author: Sonia Castelo
Author-email: s.castelo@nyu.edu
License: UNKNOWN
Platform: UNKNOWN
Classifier: Programming Language :: Python :: 3
Classifier: License :: OSI Approved :: BSD License
Classifier: Operating System :: OS Independent
Requires-Python: >=3.6
Requires-Dist: python-dateutil
Requires-Dist: numpy
Requires-Dist: scipy
Requires-Dist: scikit-learn
Requires-Dist: networkx
Requires-Dist: notebook
Requires-Dist: datamart-profiler (>=0.8)
Requires-Dist: pandas
